discake/__init__.py
discake/paginator/__init__.py
discake/utils/__init__.py
discake/utils/paginate.py
discake-0.1.0.dist-info/LICENSE
discake-0.1.0.dist-info/METADATA
discake-0.1.0.dist-info/WHEEL
discake-0.1.0.dist-info/top_level.txt
discake-0.1.0.dist-info/RECORD
