Metadata-Version: 2.1
Name: discake
Version: 0.1.0
Summary: A discord py support library containing utilities.
Home-page: https://github.com/lollipop-69/discake
Author: Carlos
License: MIT
Project-URL: Homepage, https://github.com/lollipop-69/discake/
Keywords: discord py,discord paginator,paginator,button paginator
Classifier: Development Status :: 5 - Production/Stable
Classifier: License :: OSI Approved :: MIT License
Classifier: Intended Audience :: Developers
Classifier: Natural Language :: English
Classifier: Operating System :: OS Independent
Classifier: Programming Language :: Python :: 3.8
Classifier: Programming Language :: Python :: 3.9
Classifier: Programming Language :: Python :: 3.10
Requires-Python: >=3.8.0
License-File: LICENSE
Requires-Dist: discord.py
